force_delete_win-0.1.0.dist-info/METADATA
force_delete_win-0.1.0.dist-info/WHEEL
force_delete_win/force_delete_win.pyi
force_delete_win/tests/test_delete.py
force_delete_win/tests/__init__.py
force_delete_win/__init__.py
force_delete_win/force_delete_win.cp38-win_amd64.pyd
force_delete_win-0.1.0.dist-info/RECORD
