Metadata-Version: 2.1
Name: force-delete-win
Version: 0.1.0
Classifier: Programming Language :: Rust
Classifier: Programming Language :: Python :: Implementation :: CPython
Classifier: Programming Language :: Python :: Implementation :: PyPy
Summary: Force-delete a file or folder held by other Windows processes.
Keywords: windows,delete,force,folder,file
Author: Edgar Andrés Margffoy Tuay <andfoy@gmail.com>, Stephannie Jimenez Gacha <steff456@hotmail.com>
Author-email: Edgar Andrés Margffoy Tuay <andfoy@gmail.com>, Stephannie Jimenez Gacha <steff456@hotmail.com>
License: MIT
Requires-Python: >=3.7
Project-URL: Source Code, https://github.com/andfoy/force-delete-win
